odoo10_addon_medical_practitioner-10.0.1.1.0-py2.7-nspkg.pth
odoo/addons/medical_practitioner/README.rst
odoo/addons/medical_practitioner/__init__.py
odoo/addons/medical_practitioner/__manifest__.py
odoo/addons/medical_practitioner/data/medical_role.xml
odoo/addons/medical_practitioner/i18n/fr.po
odoo/addons/medical_practitioner/i18n/nl_NL.po
odoo/addons/medical_practitioner/i18n/ro.po
odoo/addons/medical_practitioner/models/__init__.py
odoo/addons/medical_practitioner/models/medical_practitioner.py
odoo/addons/medical_practitioner/models/medical_role.py
odoo/addons/medical_practitioner/models/res_partner.py
odoo/addons/medical_practitioner/security/ir.model.access.csv
odoo/addons/medical_practitioner/static/description/icon.png
odoo/addons/medical_practitioner/tests/__init__.py
odoo/addons/medical_practitioner/tests/test_medical_practitioner.py
odoo/addons/medical_practitioner/views/medical_menu.xml
odoo/addons/medical_practitioner/views/medical_practitioner.xml
odoo/addons/medical_practitioner/views/medical_role.xml
odoo10_addon_medical_practitioner-10.0.1.1.0.dist-info/DESCRIPTION.rst
odoo10_addon_medical_practitioner-10.0.1.1.0.dist-info/METADATA
odoo10_addon_medical_practitioner-10.0.1.1.0.dist-info/RECORD
odoo10_addon_medical_practitioner-10.0.1.1.0.dist-info/WHEEL
odoo10_addon_medical_practitioner-10.0.1.1.0.dist-info/metadata.json
odoo10_addon_medical_practitioner-10.0.1.1.0.dist-info/namespace_packages.txt
odoo10_addon_medical_practitioner-10.0.1.1.0.dist-info/top_level.txt
